LICENSE
README.md
setup.py
pyncraft/__init__.py
pyncraft/block.py
pyncraft/connection.py
pyncraft/entity.py
pyncraft/event.py
pyncraft/logger.py
pyncraft/minecraft.py
pyncraft/minecraftstuff.py
pyncraft/settings.py
pyncraft/util.py
pyncraft/vec3.py
pyncraft.egg-info/PKG-INFO
pyncraft.egg-info/SOURCES.txt
pyncraft.egg-info/dependency_links.txt
pyncraft.egg-info/requires.txt
pyncraft.egg-info/top_level.txt