Metadata-Version: 2.1
Name: pyncraft
Version: 0.2.1
Summary: Python interface to minecraft + pyncraft bukkit plugin
Home-page: https://github.com/jdeast/pyncraft
Author: Jason Eastman
Author-email: jdeast@gmail.com
Keywords: minecraft,plugin,scratch,java,bukkit
Classifier: Development Status :: 3 - Alpha
Classifier: Intended Audience :: Education
Classifier: Topic :: Games/Entertainment
Classifier: License :: OSI Approved :: Apache Software License
Classifier: Programming Language :: Python :: 3
Classifier: Programming Language :: Python :: 3.6
Classifier: Programming Language :: Python :: 3.7
Classifier: Programming Language :: Python :: 3.8
Classifier: Programming Language :: Python :: 3.9
Classifier: Programming Language :: Python :: 3.10
Classifier: Programming Language :: Python :: 3 :: Only
Requires-Python: >=3.6, <4
License-File: LICENSE
